daul/__init__.py
daul/file_utils.py
daul/numpy_utils.py
daul/pandas_utils.py
daul/shortcuts.py
daul-0.1.0.dist-info/AUTHORS
daul-0.1.0.dist-info/LICENSE
daul-0.1.0.dist-info/METADATA
daul-0.1.0.dist-info/WHEEL
daul-0.1.0.dist-info/top_level.txt
daul-0.1.0.dist-info/RECORD
